wagtailtrans/__init__.py
wagtailtrans/admin.py
wagtailtrans/apps.py
wagtailtrans/conf.py
wagtailtrans/edit_handlers.py
wagtailtrans/forms.py
wagtailtrans/managers.py
wagtailtrans/middleware.py
wagtailtrans/models.py
wagtailtrans/permissions.py
wagtailtrans/signals.py
wagtailtrans/sites.py
wagtailtrans/wagtail_hooks.py
wagtailtrans/locale/zh_Hans/LC_MESSAGES/django.mo
wagtailtrans/management/__init__.py
wagtailtrans/management/commands/__init__.py
wagtailtrans/management/commands/wagtailtrans_change_default_language.py
wagtailtrans/migrations/0001_initial.py
wagtailtrans/migrations/0002_auto_20161106_1231.py
wagtailtrans/migrations/0003_auto_20161121_1211.py
wagtailtrans/migrations/0004_sitelanguages.py
wagtailtrans/migrations/0005_auto_20161130_1310.py
wagtailtrans/migrations/0006_auto_20161212_2020.py
wagtailtrans/migrations/0007_auto_20180327_1127.py
wagtailtrans/migrations/0008_verbose_names.py
wagtailtrans/migrations/0009_create_initial_language.py
wagtailtrans/migrations/__init__.py
wagtailtrans/static/.DS_Store
wagtailtrans/static/wagtailtrans/js/site_languages_editor.js
wagtailtrans/templates/wagtailadmin/pages/confirm_delete.html
wagtailtrans/templates/wagtailadmin/pages/listing/_page_title_choose.html
wagtailtrans/templates/wagtailadmin/pages/listing/_page_title_explore.html
wagtailtrans/templates/wagtailadmin/pages/listing/_page_title_move.html
wagtailtrans/templates/wagtailtrans/templatetags/language_selector.html
wagtailtrans/templates/wagtailtrans/translation/add.html
wagtailtrans/templatetags/__init__.py
wagtailtrans/templatetags/translations_wagtail_admin.py
wagtailtrans/templatetags/wagtailtrans_tags.py
wagtailtrans/urls/__init__.py
wagtailtrans/urls/translations.py
wagtailtrans/utils/__init__.py
wagtailtrans/utils/language_switch.py
wagtailtrans/views/__init__.py
wagtailtrans/views/translation.py
wagtailtrans-2.2.1.dist-info/DESCRIPTION.rst
wagtailtrans-2.2.1.dist-info/METADATA
wagtailtrans-2.2.1.dist-info/RECORD
wagtailtrans-2.2.1.dist-info/WHEEL
wagtailtrans-2.2.1.dist-info/metadata.json
wagtailtrans-2.2.1.dist-info/top_level.txt
